LICENSE
MANIFEST.in
README.md
setup.py
wlreporter/__init__.py
wlreporter/wlreporter.py
wlreporter.egg-info/PKG-INFO
wlreporter.egg-info/SOURCES.txt
wlreporter.egg-info/dependency_links.txt
wlreporter.egg-info/entry_points.txt
wlreporter.egg-info/top_level.txt