Metadata-Version: 1.0
Name: wlreporter
Version: 0.2.0
Summary: create report for wsgi_lineprof.
Home-page: https://github.com/denzow/wsgi_lineprof_reporter
Author: denzow
Author-email: denzow@gmail.com
License: MIT License
